mahiru/heart/__init__.py
mahiru/heart/heart.py
mahiru_heart-0.0.1.dist-info/METADATA
mahiru_heart-0.0.1.dist-info/WHEEL
mahiru_heart-0.0.1.dist-info/top_level.txt
mahiru_heart-0.0.1.dist-info/RECORD
